[
  {
    "domain_content": true,
    "domain_data": true,
    "domain_software": false,
    "family": "",
    "id": "ca-ogl-lgo",
    "is_okd_compliant": false,
    "is_osi_compliant": false,
    "maintainer": "",
    "status": "active",
    "title": "Open Government Licence - Canada",
    "title_fra": "Licence du gouvernement ouvert - Canada",
    "url": "http://open.canada.ca/en/open-government-licence-canada",
    "url_fra": "http://open.canada.ca/fr/licence-du-gouvernement-ouvert-canada"
  },
  {
    "domain_content": true,
    "domain_data": true,
    "domain_software": false,
    "family": "",
    "id": "ca-odla-aldg",
    "is_okd_compliant": false,
    "is_osi_compliant": false,
    "maintainer": "",
    "status": "active",
    "title": "Open Data Licence Agreement - Office of the Commissioner of Lobbying",
    "title_fra": "Accord de licence de donn\u00e9es libres - Commissariat au lobbying",
    "url": "http://lobbycanada.gc.ca/eic/site/012.nsf/eng/00873.html",
    "url_fra": "http://lobbycanada.gc.ca/eic/site/012.nsf/fra/00873.html"
  },
  {
    "domain_content": true,
    "domain_data": true,
    "domain_software": false,
    "family": "",
    "id": "ca-cihi-icis",
    "is_okd_compliant": false,
    "is_osi_compliant": false,
    "maintainer": "",
    "status": "active",
    "title": "Open Government Licence - Canadian Institute for Health Information",
    "title_fra": "Licence du gouvernement ouvert - Institut canadien d'information sur la sant\u00e9",
    "url": "http://www.cihi.ca/cihi-ext-portal/docx/internet/OPEN_GOV_LICENCE_CIHI_EN",
    "url_fra": "http://www.cihi.ca/cihi-ext-portal/docx/internet/OPEN_GOV_LICENCE_CIHI_FR"
  },
  {
    "domain_content": true,
    "domain_data": true,
    "domain_software": false,
    "family": "",
    "id": "ca-rflo-drlf",
    "is_okd_compliant": false,
    "is_osi_compliant": false,
    "maintainer": "",
    "status": "active",
    "title": "Reproduction of Federal Laws Order",
    "title_fra": "Décret sur la reproduction de la législation fédérale et des décisions des tribunaux de constitution fédérale",
    "url": "http://laws-lois.justice.gc.ca/eng/regulations/SI-97-5/FullText.html",
    "url_fra": "http://laws-lois.justice.gc.ca/fra/reglements/TR-97-5/TexteComplet.html"
  },
  {
    "domain_content": true,
    "domain_data": true,
    "domain_software": false,
    "family": "",
    "id": "ab-ogla",
    "is_okd_compliant": false,
    "is_osi_compliant": false,
    "maintainer": "",
    "status": "active",
    "title": "Open Government Licence - Alberta",
    "title_fra": "Licence du gouvernement ouvert - Alberta",
    "url": "http://open.alberta.ca/licence",
    "url_fra": "http://open.alberta.ca/licence"
  },
  {
    "domain_content": true,
    "domain_data": true,
    "domain_software": false,
    "family": "",
    "id": "ab-qptu",
    "is_okd_compliant": false,
    "is_osi_compliant": false,
    "maintainer": "",
    "status": "active",
    "title": "Alberta Queens Printer Terms of Use",
    "title_fra": "Conditions d'utilisation de l'Imprimeur de la Reine de l'Alberta",
    "url": "http://www.qp.alberta.ca/copyright.cfm",
    "url_fra": "http://www.qp.alberta.ca/copyright.cfm"
  },
    {
    "domain_content": true,
    "domain_data": true,
    "domain_software": false,
    "family": "",
    "id": "bc-oglbc",
    "is_okd_compliant": false,
    "is_osi_compliant": false,
    "maintainer": "",
    "status": "active",
    "title": "Open Government Licence - British Columbia",
    "title_fra": "Licence du gouvernement ouvert - Colombie-Britannique",
    "url": "https://www2.gov.bc.ca/gov/content/data/open-data/open-government-licence-bc",
    "url_fra": "https://www2.gov.bc.ca/gov/content/data/open-data/open-government-licence-bc"
  },
    {
    "domain_content": true,
    "domain_data": true,
    "domain_software": false,
    "family": "",
    "id": "nl-oglnl",
    "is_okd_compliant": false,
    "is_osi_compliant": false,
    "maintainer": "",
    "status": "active",
    "title": "Open Government Licence – Newfoundland and Labrador",
    "title_fra": "Licence du gouvernement ouvert – Terre-Neuve-et-Labrador",
    "url": "https://opendata.gov.nl.ca/public/opendata/page/?page-id=licence",
    "url_fra": "https://opendata.gov.nl.ca/public/opendata/page/?page-id=licence"
  },
    {
    "domain_content": true,
    "domain_data": true,
    "domain_software": false,
    "family": "",
    "id": "ns-oglns",
    "is_okd_compliant": false,
    "is_osi_compliant": false,
    "maintainer": "",
    "status": "active",
    "title": "Open Government Licence – Nova Scotia",
    "title_fra": "Licence du gouvernement ouvert – Nouvelle-Écosse",
    "url": "https://novascotia.ca/opendata/licence.asp",
    "url_fra": "https://novascotia.ca/opendata/licence.asp"
  },
    {
    "domain_content": true,
    "domain_data": true,
    "domain_software": false,
    "family": "",
    "id": "on-oglo",
    "is_okd_compliant": false,
    "is_osi_compliant": false,
    "maintainer": "",
    "status": "active",
    "title": "Open Government Licence – Ontario",
    "title_fra": "Licence du gouvernement ouvert – Ontario",
    "url": "https://www.ontario.ca/page/open-government-licence-ontario",
    "url_fra": "https://www.ontario.ca/fr/page/licence-du-gouvernement-ouvert-Ontario"
  },
    {
    "domain_content": true,
    "domain_data": true,
    "domain_software": false,
    "family": "",
    "id": "pei-oglpei",
    "is_okd_compliant": false,
    "is_osi_compliant": false,
    "maintainer": "",
    "status": "active",
    "title": "Open Government Licence – Prince Edward Island",
    "title_fra": "Licence du gouvernement ouvert – Île-du-Prince-Édouard",
    "url": "https://www.princeedwardisland.ca/en/information/finance/open-government-licence-prince-edward-island",
    "url_fra": "https://www.princeedwardisland.ca/fr/information/finances/licence-du-gouvernement-ouvert-ile-du-prince-edouard"
  },
  {
    "domain_content": true,
    "domain_data": true,
    "domain_software": false,
    "family": "",
    "id": "nb-oglnb",
    "is_okd_compliant": false,
    "is_osi_compliant": false,
    "maintainer": "",
    "status": "active",
    "title": "Open Government Licence - New Brunswick",
    "title_fra": "Licence du gouvernement ouvert - Nouveau-Brunswick",
    "url": "http://www.snb.ca/e/2000/data-E.html",
    "url_fra": "http://www.snb.ca/f/2000/data-F.html"
  },
  {
    "domain_content": true,
    "domain_data": true,
    "domain_software": false,
    "family": "",
    "id": "yk-oglyk",
    "is_okd_compliant": false,
    "is_osi_compliant": false,
    "maintainer": "",
    "status": "active",
    "title": "Open Government Licence – Yukon",
    "title_fra": "Licence du gouvernement ouvert – Yukon",
    "url": "https://open.yukon.ca/data/open-government-licence-yukon",
    "url_fra": "https://open.yukon.ca/data/fr/gouvernement-ouvert-licence-du-yukon"
  },
  {
    "domain_content": true,
    "domain_data": true,
    "domain_software": false,
    "family": "",
    "id": "qc-oglqc",
    "is_okd_compliant": false,
    "is_osi_compliant": false,
    "maintainer": "",
    "status": "active",
    "title": "Creative Commons 4.0 Attribution (CC-BY) licence – Quebec",
    "title_fra": "Licence Creative Commons 4.0 Attribution (CC-BY) – Québec",
    "url": "https://www.donneesquebec.ca/fr/licence/",
    "url_fra": "https://www.donneesquebec.ca/fr/licence/"
  }
]
